{
    "fr": {
        "meta_title": "Bistrot d'Antoine — Bistrot français traditionnel à Nice",
        "meta_description": "Bistrot d'Antoine — bistrot de référence à Nice, ardoise du marché, vins du Sud, plats bistronomiques. 27 rue de la Préfecture, Vieux-Nice. Réservation recommandée.",
        "strip_open_label": "Ouvert",
        "strip_open_value": "Mar – Sam",
        "strip_service_label": "Services",
        "strip_service_value": "Midi & Soir",
        "strip_book_label": "Réservation",
        "strip_book_value": "Recommandée",
        "strip_price_label": "Prix moyen",
        "strip_price_value": "30–40 €",
        "arguments": [
            {
                "icon": "chef-hat",
                "title": "Ardoise de marché renouvelée",
                "description": "La carte change selon les arrivages du Cours Saleya, tout proche. Produits frais, saison garantie, jamais le même menu deux semaines de suite."
            },
            {
                "icon": "award",
                "title": "Bib Gourmand Michelin",
                "description": "Distingué par le Guide Michelin pour son excellence et son rapport qualité-prix, le restaurant s'est imposé comme la référence bistronomique du Vieux-Nice."
            },
            {
                "icon": "wine",
                "title": "Belle carte des vins du Sud",
                "description": "Une sélection de vins régionaux abordables, avec Sauvignon de Touraine et cuvées locales pour accompagner une cuisine généreuse aux accents méditerranéens."
            }
        ],
        "menu_preview_starters": [
            { "name": "Pâté de Campagne Maison", "price": "12 €" },
            { "name": "Mousse de Chou-fleur, Vinaigrette Yuzu, Bottarga", "price": "13 €" },
            { "name": "Tartare de Veau, Chimichurri, Pecorino", "price": "15 €" }
        ],
        "menu_preview_mains": [
            { "name": "Filet de Rouget, Petits Pois, Beurre Blanc Béarnaise", "price": "30 €" },
            { "name": "Filet de Cabillaud, Condiment Kiwi-Céleri", "price": "26 €" },
            { "name": "Joues de Porc Braisées, Polenta Crémeuse", "price": "18 €" }
        ],
        "menu_preview_desserts": [
            { "name": "Poire Conférence Pochée", "price": "9 €" },
            { "name": "Baba au Rhum Maison", "price": "9 €" },
            { "name": "Fondant Chocolat, Fruits Secs Caramélisés", "price": "8 €" }
        ],
        "menu_preview_formulas": [],
        "gallery_images": [
            {
                "src": "https://images.unsplash.com/photo-1414235077428-338989a2e8c0?w=1200&q=80&auto=format&fit=crop",
                "alt": "Salle du Bistrot d'Antoine — Nice",
                "variant": "wide"
            },
            {
                "src": "https://images.unsplash.com/photo-1504674900247-0877df9cc836?w=600&q=80&auto=format&fit=crop",
                "alt": "Plat du chef — Bistrot d'Antoine Nice",
                "variant": "tall"
            },
            {
                "src": "https://images.unsplash.com/photo-1496116218417-1a781b1c416c?w=600&q=80&auto=format&fit=crop",
                "alt": "Détail de table — Bistrot d'Antoine",
                "variant": "normal"
            },
            {
                "src": "https://images.unsplash.com/photo-1510812431401-41d2bd2722f3?w=600&q=80&auto=format&fit=crop",
                "alt": "Cave à vins — Bistrot d'Antoine Nice",
                "variant": "normal"
            },
            {
                "src": "https://images.unsplash.com/photo-1556909114-f6e7ad7d3136?w=600&q=80&auto=format&fit=crop",
                "alt": "En cuisine — Bistrot d'Antoine",
                "variant": "tall"
            },
            {
                "src": "https://images.unsplash.com/photo-1555396273-367ea4eb4db5?w=600&q=80&auto=format&fit=crop",
                "alt": "Terrasse rue de la Préfecture — Nice",
                "variant": "normal"
            },
            {
                "src": "https://images.unsplash.com/photo-1563805042-7684c019e1cb?w=600&q=80&auto=format&fit=crop",
                "alt": "Dessert signature — Bistrot d'Antoine",
                "variant": "normal"
            },
            {
                "src": "https://images.unsplash.com/photo-1424847651672-bf20a4b0982b?w=1200&q=80&auto=format&fit=crop",
                "alt": "Ambiance salle — Bistrot d'Antoine Nice",
                "variant": "wide"
            }
        ],
        "reviews": [
            {
                "author": "Sophie M.",
                "date": "Novembre 2025",
                "rating": 5,
                "comment": "Une cuisine bistronomique impressionnante pour un simple bistrot de quartier. De l'entrée au dessert, tout était délicieux, le service rapide et agréable. Une adresse incontournable à Nice."
            },
            {
                "author": "Thomas B.",
                "date": "Octobre 2025",
                "rating": 5,
                "comment": "Le tartare de bœuf et les joues de porc braisées étaient tout simplement parfaits. Les vins proposés sont bien choisis et accessibles. Il faut absolument réserver à l'avance !"
            },
            {
                "author": "Claire V.",
                "date": "Septembre 2025",
                "rating": 5,
                "comment": "Meilleure adresse de notre séjour niçois, et de loin. L'ardoise change régulièrement, la cuisine est sincère et créative. On est repartis avec l'envie d'y retourner dès le lendemain."
            }
        ]
    },
    "en": {
        "meta_title": "Bistrot d'Antoine — Traditional French Bistro in Nice",
        "meta_description": "Bistrot d'Antoine — a landmark bistro in Nice, seasonal chalkboard menu, southern wines, bistronomy dishes. 27 rue de la Préfecture, Vieux-Nice. Reservations recommended.",
        "strip_open_label": "Open",
        "strip_open_value": "Tue – Sat",
        "strip_service_label": "Service",
        "strip_service_value": "Lunch & Dinner",
        "strip_book_label": "Reservations",
        "strip_book_value": "Recommended",
        "strip_price_label": "Average spend",
        "strip_price_value": "€30–40",
        "arguments": [
            {
                "icon": "chef-hat",
                "title": "Rotating market-fresh menu",
                "description": "The chalkboard changes with deliveries from the nearby Cours Saleya market. Fresh produce, seasonal guarantee — never the same menu two weeks running."
            },
            {
                "icon": "award",
                "title": "Michelin Bib Gourmand",
                "description": "Recognised by the Michelin Guide for its quality and outstanding value, the restaurant has established itself as the bistronomic benchmark of Vieux-Nice."
            },
            {
                "icon": "wine",
                "title": "Affordable southern wine list",
                "description": "A selection of accessible regional wines, with local cuvées and Loire Valley finds to complement generous, Mediterranean-inflected cuisine."
            }
        ],
        "menu_preview_starters": [
            { "name": "Homemade Country Pâté", "price": "€12" },
            { "name": "Cauliflower Foam, Yuzu Vinaigrette, Bottarga", "price": "€13" },
            { "name": "Veal Tartare, Chimichurri, Pecorino", "price": "€15" }
        ],
        "menu_preview_mains": [
            { "name": "Redfish Fillet, Spring Peas, Béarnaise Butter", "price": "€30" },
            { "name": "Cod Fillet, Kiwi & Celery Condiment", "price": "€26" },
            { "name": "Braised Pork Cheeks, Creamy Polenta", "price": "€18" }
        ],
        "menu_preview_desserts": [
            { "name": "Poached Conférence Pear", "price": "€9" },
            { "name": "Classic Rum Baba", "price": "€9" },
            { "name": "Chocolate Fondant, Caramelised Nuts", "price": "€8" }
        ],
        "menu_preview_formulas": [],
        "gallery_images": [
            {
                "src": "https://images.unsplash.com/photo-1414235077428-338989a2e8c0?w=1200&q=80&auto=format&fit=crop",
                "alt": "Dining room — Bistrot d'Antoine Nice",
                "variant": "wide"
            },
            {
                "src": "https://images.unsplash.com/photo-1504674900247-0877df9cc836?w=600&q=80&auto=format&fit=crop",
                "alt": "Chef's dish — Bistrot d'Antoine Nice",
                "variant": "tall"
            },
            {
                "src": "https://images.unsplash.com/photo-1496116218417-1a781b1c416c?w=600&q=80&auto=format&fit=crop",
                "alt": "Table detail — Bistrot d'Antoine",
                "variant": "normal"
            },
            {
                "src": "https://images.unsplash.com/photo-1510812431401-41d2bd2722f3?w=600&q=80&auto=format&fit=crop",
                "alt": "Wine selection — Bistrot d'Antoine Nice",
                "variant": "normal"
            },
            {
                "src": "https://images.unsplash.com/photo-1556909114-f6e7ad7d3136?w=600&q=80&auto=format&fit=crop",
                "alt": "Kitchen — Bistrot d'Antoine",
                "variant": "tall"
            },
            {
                "src": "https://images.unsplash.com/photo-1555396273-367ea4eb4db5?w=600&q=80&auto=format&fit=crop",
                "alt": "Terrace on rue de la Préfecture — Nice",
                "variant": "normal"
            },
            {
                "src": "https://images.unsplash.com/photo-1563805042-7684c019e1cb?w=600&q=80&auto=format&fit=crop",
                "alt": "Signature dessert — Bistrot d'Antoine",
                "variant": "normal"
            },
            {
                "src": "https://images.unsplash.com/photo-1424847651672-bf20a4b0982b?w=1200&q=80&auto=format&fit=crop",
                "alt": "Dining room ambiance — Bistrot d'Antoine Nice",
                "variant": "wide"
            }
        ],
        "reviews": [
            {
                "author": "Sophie M.",
                "date": "November 2025",
                "rating": 5,
                "comment": "Impressive bistronomy for what is essentially a neighbourhood bistro. Every dish from starter to dessert was delicious, service was quick and attentive. A must in Nice."
            },
            {
                "author": "Thomas B.",
                "date": "October 2025",
                "rating": 5,
                "comment": "The beef tartare and braised pork cheeks were simply perfect. The wine list is well-chosen and accessible. Make sure to book well in advance!"
            },
            {
                "author": "Claire V.",
                "date": "September 2025",
                "rating": 5,
                "comment": "The best table of our stay in Nice by a long stretch. The menu changes regularly, the cooking is honest and creative. We left wanting to come back the very next day."
            }
        ]
    }
}
